architect/__init__.py
architect/core/__init__.py
architect/core/logging.py
architect/core/schemas.py
architect/providers/__init__.py
architect/providers/base.py
canary_io-0.0.1.dist-info/METADATA
canary_io-0.0.1.dist-info/WHEEL
canary_io-0.0.1.dist-info/top_level.txt
canary_io-0.0.1.dist-info/RECORD
